{
  "area_1": {
    "coord": [
      {
        "x": 460,
        "y": 450
      },
      {
        "x": 750,
        "y": 450
      },
      {
        "x": 721,
        "y": 662
      },
      {
        "x": 149,
        "y": 662
      }
    ],
    "distance": 15
  },
  "area_2": {
    "coord": [
      {
        "x": 791,
        "y": 448
      },
      {
        "x": 1080,
        "y": 448
      },
      {
        "x": 1334,
        "y": 573
      },
      {
        "x": 831,
        "y": 573
      }
    ],
    "distance": 15
  }
}
